klampt_jupyter/__init__.py
klampt_jupyter/_frontend.py
klampt_jupyter/_version.py
klampt_jupyter/widget.py
klampt_jupyter/labextension/build_log.json
klampt_jupyter/labextension/package.json
klampt_jupyter/labextension/static/lib_index_js.dedfb8fee9fb894fb3db.js
klampt_jupyter/labextension/static/lib_index_js.dedfb8fee9fb894fb3db.js.map
klampt_jupyter/labextension/static/lib_plugin_js.b70f9c3cefe86a755e18.js
klampt_jupyter/labextension/static/lib_plugin_js.b70f9c3cefe86a755e18.js.map
klampt_jupyter/labextension/static/lib_widget_js.f3afe5bee65feee5451f.js
klampt_jupyter/labextension/static/lib_widget_js.f3afe5bee65feee5451f.js.map
klampt_jupyter/labextension/static/remoteEntry.d4f4bd6f9e169a9b8fba.js
klampt_jupyter/labextension/static/remoteEntry.d4f4bd6f9e169a9b8fba.js.map
klampt_jupyter/labextension/static/style.js
klampt_jupyter/labextension/static/vendors-node_modules_three-trackballcontrols-ts_dist_index_js.5e1d99363266eb24001b.js
klampt_jupyter/labextension/static/vendors-node_modules_three-trackballcontrols-ts_dist_index_js.5e1d99363266eb24001b.js.map
klampt_jupyter/labextension/static/vendors-node_modules_three_build_three_module_js.86a3ee8484757fdb9ec0.js
klampt_jupyter/labextension/static/vendors-node_modules_three_build_three_module_js.86a3ee8484757fdb9ec0.js.map
klampt_jupyter/nbextension/extension.js
klampt_jupyter/nbextension/index.js
klampt_jupyter/nbextension/index.js.map
klampt_jupyter/tests/__init__.py
klampt_jupyter/tests/conftest.py
klampt_jupyter/tests/test_example.py
klampt_jupyter/tests/test_nbextension_path.py
klampt_jupyter-0.1.2.data/data/etc/jupyter/nbconfig/notebook.d/klampt_jupyter.json
klampt_jupyter-0.1.2.data/data/share/jupyter/labextensions/klampt-jupyter-widget/build_log.json
klampt_jupyter-0.1.2.data/data/share/jupyter/labextensions/klampt-jupyter-widget/install.json
klampt_jupyter-0.1.2.data/data/share/jupyter/labextensions/klampt-jupyter-widget/package.json
klampt_jupyter-0.1.2.dist-info/LICENSE.txt
klampt_jupyter-0.1.2.dist-info/METADATA
klampt_jupyter-0.1.2.dist-info/WHEEL
klampt_jupyter-0.1.2.dist-info/top_level.txt
klampt_jupyter-0.1.2.dist-info/RECORD
